README.md
setup.py
Flask_SSS.egg-info/PKG-INFO
Flask_SSS.egg-info/SOURCES.txt
Flask_SSS.egg-info/dependency_links.txt
Flask_SSS.egg-info/requires.txt
Flask_SSS.egg-info/top_level.txt
flask_sss/__init__.py
flask_sss/__version__.py