Metadata-Version: 2.1
Name: Flask-SSS
Version: 0.1.0
Summary: Server-Side Sessions for Flask implemented as a SessionInterface.
Home-page: https://github.com/stevemccartney/flask-sss
Author: Steve McCartney
Author-email: python@reconvergent.com
License: Apache 2.0
Keywords: flask server-side sessions sqlalchemy
Platform: UNKNOWN
Classifier: Development Status :: 4 - Beta
Classifier: Intended Audience :: Developers
Classifier: Programming Language :: Python :: 3.8
Requires-Python: >=3.8.*
